neonex_theme/__init__.py
neonex_theme/_version.py
neonex_theme-1.0.0.data/data/share/jupyter/labextensions/neonex-theme/build_log.json
neonex_theme-1.0.0.data/data/share/jupyter/labextensions/neonex-theme/package.json
neonex_theme-1.0.0.data/data/share/jupyter/labextensions/neonex-theme/static/lib_index_js.3b50cbbb905145b4c322.js
neonex_theme-1.0.0.data/data/share/jupyter/labextensions/neonex-theme/static/lib_index_js.3b50cbbb905145b4c322.js.map
neonex_theme-1.0.0.data/data/share/jupyter/labextensions/neonex-theme/static/remoteEntry.12526c0173d124d3bb4a.js
neonex_theme-1.0.0.data/data/share/jupyter/labextensions/neonex-theme/static/remoteEntry.12526c0173d124d3bb4a.js.map
neonex_theme-1.0.0.data/data/share/jupyter/labextensions/neonex-theme/static/style.js
neonex_theme-1.0.0.data/data/share/jupyter/labextensions/neonex-theme/themes/neonex-theme/31c92d01a8a08528b718.ttf
neonex_theme-1.0.0.data/data/share/jupyter/labextensions/neonex-theme/themes/neonex-theme/6a4fa3b6640928748c36.otf
neonex_theme-1.0.0.data/data/share/jupyter/labextensions/neonex-theme/themes/neonex-theme/8391e7ec13e8ba758c18.ttf
neonex_theme-1.0.0.data/data/share/jupyter/labextensions/neonex-theme/themes/neonex-theme/8e501d3a6a883e83ea4f.ttf
neonex_theme-1.0.0.data/data/share/jupyter/labextensions/neonex-theme/themes/neonex-theme/ca38814915c80dfd20bb.png
neonex_theme-1.0.0.data/data/share/jupyter/labextensions/neonex-theme/themes/neonex-theme/index.css
neonex_theme-1.0.0.data/data/share/jupyter/labextensions/neonex-theme/themes/neonex-theme/index.js
neonex_theme-1.0.0.data/data/share/jupyter/labextensions/neonex-theme/install.json
neonex_theme-1.0.0.dist-info/METADATA
neonex_theme-1.0.0.dist-info/WHEEL
neonex_theme-1.0.0.dist-info/licenses/LICENSE
neonex_theme-1.0.0.dist-info/RECORD
