Metadata-Version: 2.4
Name: neonex_theme
Version: 1.0.0
Dynamic: Keywords
Summary: A Neonex Theme for Jupyter Lab
Project-URL: Homepage, https://github.com/jaremari/neonex_theme
Project-URL: Bug Tracker, https://github.com/jaremari/neonex_theme/issues
Project-URL: Repository, https://github.com/jaremari/neonex_theme.git
Author-email: Jarema Marinez <jarema.marinez@neonex.de>
License: BSD 3-Clause License
License-File: LICENSE
Classifier: Framework :: Jupyter
Classifier: Framework :: Jupyter :: JupyterLab
Classifier: Framework :: Jupyter :: JupyterLab :: 4
Classifier: Framework :: Jupyter :: JupyterLab :: Extensions
Classifier: Framework :: Jupyter :: JupyterLab :: Extensions :: Prebuilt
Classifier: License :: OSI Approved :: BSD License
Classifier: Programming Language :: Python
Classifier: Programming Language :: Python :: 3
Classifier: Programming Language :: Python :: 3.8
Classifier: Programming Language :: Python :: 3.9
Classifier: Programming Language :: Python :: 3.10
Classifier: Programming Language :: Python :: 3.11
Requires-Python: >=3.8
